vizutils/__init__.py
vizutils/advanced_plots.py
vizutils/basic_plots.py
vizutils/interactive_plots.py
vizutils-0.1.1.dist-info/METADATA
vizutils-0.1.1.dist-info/WHEEL
vizutils-0.1.1.dist-info/top_level.txt
vizutils-0.1.1.dist-info/RECORD
