Metadata-Version: 2.1
Name: vizutils
Version: 0.1.1
Summary: A library for creating visualizations for data analysis.
Home-page: https://github.com/omkars20/vizutils_package.git
Author: Omkar Singh
Author-email: singhomkar20.1995@gmail.com
Classifier: Programming Language :: Python :: 3
Classifier: License :: OSI Approved :: MIT License
Classifier: Operating System :: OS Independent
Requires-Python: >=3.6
Requires-Dist: matplotlib
Requires-Dist: seaborn
Requires-Dist: plotly
Requires-Dist: pandas
